vaidyaraj/__init__.py
vaidyaraj/__main__.py
vaidyaraj/main.py
vaidyaraj-1.1.dist-info/METADATA
vaidyaraj-1.1.dist-info/WHEEL
vaidyaraj-1.1.dist-info/top_level.txt
vaidyaraj-1.1.dist-info/RECORD
