Metadata-Version: 2.1
Name: vaidyaraj
Version: 1.1
Summary: Introducing Vaidyanath: The Future of Holistic Health Assistance! 🌿💥
Author: Suraj Sharma
Author-email: Surajsharma963472@gmail.com
Keywords: Surya,Vaidya,Vaidyanath,python tutorial,Suraj,Doctor,groq
Requires-Dist: pathlib
Requires-Dist: colorama
Requires-Dist: edge-tts
Requires-Dist: pygame
Requires-Dist: groq
